BankAccountNumber/BankAccountNumber.py
BankAccountNumber/__init__.py
BankAccountNumber/iban.py
BankAccountNumber/version.py
robotframework_bankaccountnumber-0.3.dist-info/METADATA
robotframework_bankaccountnumber-0.3.dist-info/WHEEL
robotframework_bankaccountnumber-0.3.dist-info/top_level.txt
robotframework_bankaccountnumber-0.3.dist-info/RECORD
